david8_clickhouse/__init__.py
david8_clickhouse/cast_types.py
david8_clickhouse/functions_conditional.py
david8_clickhouse/functions_dates_times.py
david8_clickhouse/functions_dict.py
david8_clickhouse/functions_str.py
david8_clickhouse/functions_table.py
david8_clickhouse/input_output_formats.py
david8_clickhouse/joins.py
david8_clickhouse/core/__init__.py
david8_clickhouse/core/array_join.py
david8_clickhouse/core/ddl.py
david8_clickhouse/core/dml.py
david8_clickhouse/core/drop_partitions.py
david8_clickhouse/core/expressions.py
david8_clickhouse/core/query_builder.py
david8_clickhouse/core/select_query.py
david8_clickhouse/core/table_functions.py
david8_clickhouse/protocols/__init__.py
david8_clickhouse/protocols/query_builder.py
david8_clickhouse/protocols/sql.py
david8_clickhouse-0.5.0b1.dist-info/licenses/LICENSE
david8_clickhouse-0.5.0b1.dist-info/METADATA
david8_clickhouse-0.5.0b1.dist-info/WHEEL
david8_clickhouse-0.5.0b1.dist-info/top_level.txt
david8_clickhouse-0.5.0b1.dist-info/RECORD
