Metadata-Version: 2.4
Name: david8_clickhouse
Version: 0.5.0b1
Summary: SQL query builder. david8 ClickHouse dielect
Author-email: Danila Ganchar <danila.ganchar@gmail.com>
Maintainer-email: Danila Ganchar <danila.ganchar@gmail.com>
Project-URL: Homepage, https://github.com/d-ganchar/david8_clickhouse
Project-URL: Changelog, https://github.com/d-ganchar/david8_clickhouse/releases
Project-URL: Issues, https://github.com/d-ganchar/david8_clickhouse/issues
Project-URL: CI, https://github.com/d-ganchar/david8_clickhouse/actions
Project-URL: Documentation, https://github.com/d-ganchar/david8_clickhouse/wiki
Project-URL: Source, https://github.com/d-ganchar/david8_clickhouse
Classifier: Development Status :: 4 - Beta
Classifier: Intended Audience :: Developers
Classifier: Topic :: Software Development :: Libraries
Classifier: Topic :: Database
Classifier: Programming Language :: Python :: 3
Classifier: Programming Language :: Python :: 3.11
Classifier: Programming Language :: Python :: 3.12
Classifier: Programming Language :: Python :: 3.13
Requires-Python: <3.14,>=3.11
License-File: LICENSE
Requires-Dist: david8<2.0.0b1,>=1.0.0b1
Dynamic: license-file
